abrviz/__init__.py
abrviz/abrviz.py
abrviz-0.3.dist-info/METADATA
abrviz-0.3.dist-info/WHEEL
abrviz-0.3.dist-info/top_level.txt
abrviz-0.3.dist-info/RECORD
