Metadata-Version: 2.1
Name: abrviz
Version: 0.3
Summary: Visualisation Arbre Binaire de Recherche
Home-page: https://github.com/cobacdavid/abrviz
Author: David COBAC
Author-email: david.cobac@gmail.com
License: CC-BY-NC-SA
Keywords: bst,abr,sort,tri,tree,arbre
Platform: UNKNOWN
Requires-Python: >3.5
Requires-Dist: graphviz
